pyzurecli/.deprecated/graph_api.py
pyzurecli/.deprecated/pyzureserver.py
pyzurecli/__init__.py
pyzurecli/app_registration.py
pyzurecli/factory.py
pyzurecli/models.py
pyzurecli/pkg_graph_api/__init__.py
pyzurecli/pkg_graph_api/class_graph_api.py
pyzurecli/pkg_graph_api/mod_util.py
pyzurecli/pkg_graph_api/pkg_filters/__init__.py
pyzurecli/pkg_graph_api/pkg_filters/mod_email_filters.py
pyzurecli/pkg_graph_api/pkg_filters/mod_people_filters.py
pyzurecli/pkg_graph_api/pkg_filters/test_email_features.py
pyzurecli/pkg_graph_api/pkg_messages/.gitignore
pyzurecli/pkg_graph_api/pkg_messages/__init__.py
pyzurecli/pkg_graph_api/pkg_messages/mod_get_messages.py
pyzurecli/pkg_graph_api/pkg_messages/mod_list_messages.py
pyzurecli/pkg_graph_api/pkg_messages/test_list_messages.py
pyzurecli/pkg_graph_api/pkg_safe_request/__init__.py
pyzurecli/pkg_graph_api/pkg_safe_request/mod_safe_request.py
pyzurecli/pkg_graph_api/pkg_sanitize_email/__init__.py
pyzurecli/pkg_graph_api/pkg_sanitize_email/test.html
pyzurecli/pkg_graph_api/pkg_todos/__init__.py
pyzurecli/pkg_graph_api/pkg_type_check_emails/__init__.py
pyzurecli/pkg_graph_api/pkg_type_check_emails/mock_type_check_emails.py
pyzurecli/pkg_graph_api/pkg_type_check_emails/mod_type_check_emails.py
pyzurecli/pkg_graph_api/pkg_type_check_emails/test_type_check_emails.py
pyzurecli/sp.py
pyzurecli/user.py
pyzurecli/util.py
pyzurecli-0.7.522.dist-info/licenses/LICENSE
pyzurecli-0.7.522.dist-info/METADATA
pyzurecli-0.7.522.dist-info/WHEEL
pyzurecli-0.7.522.dist-info/RECORD
